timewise_sup/__init__.py
timewise_sup/ampel_conf.py
timewise_sup/analyse_lightcurves/__init__.py
timewise_sup/analyse_lightcurves/bayesian_blocks.py
timewise_sup/analyse_lightcurves/cluster.py
timewise_sup/analyse_lightcurves/create_job_file_yaml.py
timewise_sup/config_loader.py
timewise_sup/environment.py
timewise_sup/main.py
timewise_sup/meta_analysis/__init__.py
timewise_sup/meta_analysis/agn.py
timewise_sup/meta_analysis/baseline_subtraction.py
timewise_sup/meta_analysis/catalog_match.py
timewise_sup/meta_analysis/diagnostics.py
timewise_sup/meta_analysis/fluence.py
timewise_sup/meta_analysis/flux.py
timewise_sup/meta_analysis/integrate_time.py
timewise_sup/meta_analysis/ir_energy.py
timewise_sup/meta_analysis/luminosity.py
timewise_sup/meta_analysis/plot_tns_matches.py
timewise_sup/meta_analysis/rejection_reason.py
timewise_sup/meta_analysis/separation.py
timewise_sup/mongo.py
timewise_sup/plots/__init__.py
timewise_sup/plots/chi2_histograms.py
timewise_sup/plots/color_plots.py
timewise_sup/plots/diagnostic_plots.py
timewise_sup/plots/ensemble_lightcurves.py
timewise_sup/plots/ir_energies.py
timewise_sup/plots/plot_lightcurves.py
timewise_sup/plots/rise_fade_times.py
timewise_sup/plots/test_data_res.py
timewise_sup/samples/bts.py
timewise_sup/samples/data/test_sample.json
timewise_sup/samples/sjoerts_flares.py
timewise_sup/sky_match.py
timewise_sup-0.5.0.dist-info/LICENSE
timewise_sup-0.5.0.dist-info/METADATA
timewise_sup-0.5.0.dist-info/WHEEL
timewise_sup-0.5.0.dist-info/entry_points.txt
timewise_sup-0.5.0.dist-info/RECORD
