Metadata-Version: 2.1
Name: timewise-sup
Version: 0.5.0
Summary: The Timewise Subtraction Pipeline produces mid-infrared difference photometry based on measurements by the WISE satelite
Home-page: https://gitlab.desy.de/jannisnecker/timewise_sup
License: BSD-3-Clause
Author: Jannis Necker
Author-email: jannis.necker@gmail.com
Requires-Python: >=3.10,<3.11
Classifier: License :: OSI Approved :: BSD License
Classifier: Programming Language :: Python :: 3
Classifier: Programming Language :: Python :: 3.10
Provides-Extra: fpbot
Provides-Extra: jupyter
Requires-Dist: ampel-core (==0.8.4)
Requires-Dist: ampel-hu-astro[ztf] (==0.8.3a20)
Requires-Dist: corner (>=2.2.1,<3.0.0)
Requires-Dist: extcats (>=2.4.3,<3.0.0)
Requires-Dist: jupyterlab (>=4.0.0,<5.0.0) ; extra == "jupyter"
Requires-Dist: matplotlib-venn (>=0.11.9,<0.12.0)
Requires-Dist: more-itertools (>=9.0.0,<10.0.0)
Requires-Dist: nltk (>=3.7,<4.0)
Requires-Dist: scikit-learn (>=1.1.2,<2.0.0)
Requires-Dist: timewise (==0.4.10)
Requires-Dist: tkpdfviewer (>=0.1,<0.2)
Requires-Dist: uncertainties (>=3.1.7,<4.0.0)
Project-URL: Documentation, https://jannisnecker.pages.desy.de/timewise_sup/docs/
Project-URL: Repository, https://gitlab.desy.de/jannisnecker/timewise_sup
